<annotation>
	<folder>dataset_2</folder>
	<filename>rock20pigeon140.jpeg</filename>
	<path>/Users/macnp/Library/CloudStorage/OneDrive-Personal/skole/CPH Business DAT/4. Semester/Python_and_Data_science/EksamensProjectDataScience/SSD300/dataset_2/rock20pigeon140.jpeg</path>
	<source>
		<database>Unknown</database>
	</source>
	<size>
		<width>1920</width>
		<height>1080</height>
		<depth>3</depth>
	</size>
	<segmented>0</segmented>
	<object>
		<name>Flying Rat</name>
		<pose>Unspecified</pose>
		<truncated>0</truncated>
		<difficult>0</difficult>
		<bndbox>
			<xmin>64</xmin>
			<ymin>59</ymin>
			<xmax>308</xmax>
			<ymax>301</ymax>
		</bndbox>
	</object>
	<object>
		<name>Flying Rat</name>
		<pose>Unspecified</pose>
		<truncated>0</truncated>
		<difficult>0</difficult>
		<bndbox>
			<xmin>64</xmin>
			<ymin>425</ymin>
			<xmax>332</xmax>
			<ymax>671</ymax>
		</bndbox>
	</object>
	<object>
		<name>Flying Rat</name>
		<pose>Unspecified</pose>
		<truncated>0</truncated>
		<difficult>0</difficult>
		<bndbox>
			<xmin>62</xmin>
			<ymin>791</ymin>
			<xmax>294</xmax>
			<ymax>1016</ymax>
		</bndbox>
	</object>
	<object>
		<name>Flying Rat</name>
		<pose>Unspecified</pose>
		<truncated>0</truncated>
		<difficult>0</difficult>
		<bndbox>
			<xmin>406</xmin>
			<ymin>54</ymin>
			<xmax>1555</xmax>
			<ymax>1048</ymax>
		</bndbox>
	</object>
	<object>
		<name>Flying Rat</name>
		<pose>Unspecified</pose>
		<truncated>0</truncated>
		<difficult>0</difficult>
		<bndbox>
			<xmin>1608</xmin>
			<ymin>112</ymin>
			<xmax>1872</xmax>
			<ymax>314</ymax>
		</bndbox>
	</object>
	<object>
		<name>Flying Rat</name>
		<pose>Unspecified</pose>
		<truncated>0</truncated>
		<difficult>0</difficult>
		<bndbox>
			<xmin>1587</xmin>
			<ymin>471</ymin>
			<xmax>1881</xmax>
			<ymax>640</ymax>
		</bndbox>
	</object>
	<object>
		<name>Flying Rat</name>
		<pose>Unspecified</pose>
		<truncated>0</truncated>
		<difficult>0</difficult>
		<bndbox>
			<xmin>1596</xmin>
			<ymin>805</ymin>
			<xmax>1906</xmax>
			<ymax>1035</ymax>
		</bndbox>
	</object>
</annotation>
