<annotation>
	<folder></folder>
	<filename>Rock-Pigeon-193_jpg.rf.72a392075f5fd4b9bb31b77e4e0768b3.jpg</filename>
	<path>Rock-Pigeon-193_jpg.rf.72a392075f5fd4b9bb31b77e4e0768b3.jpg</path>
	<source>
		<database>roboflow.ai</database>
	</source>
	<size>
		<width>416</width>
		<height>416</height>
		<depth>3</depth>
	</size>
	<segmented>0</segmented>
	<object>
		<name>Rock Pigeon</name>
		<pose>Unspecified</pose>
		<truncated>0</truncated>
		<difficult>0</difficult>
		<occluded>0</occluded>
		<bndbox>
			<xmin>175</xmin>
			<xmax>405</xmax>
			<ymin>153</ymin>
			<ymax>368</ymax>
		</bndbox>
	</object>
	<object>
		<name>Rock Pigeon</name>
		<pose>Unspecified</pose>
		<truncated>0</truncated>
		<difficult>0</difficult>
		<occluded>0</occluded>
		<bndbox>
			<xmin>186</xmin>
			<xmax>293</xmax>
			<ymin>30</ymin>
			<ymax>153</ymax>
		</bndbox>
	</object>
</annotation>
